tests/__init__.py
vhr_composite/__init__.py
vhr_composite/model/__init__.py
vhr_composite/model/composite.py
vhr_composite/model/metrics.py
vhr_composite/model/post_process.py
vhr_composite/model/utils.py
vhr_composite-0.0.1.dist-info/LICENSE
vhr_composite-0.0.1.dist-info/METADATA
vhr_composite-0.0.1.dist-info/WHEEL
vhr_composite-0.0.1.dist-info/top_level.txt
vhr_composite-0.0.1.dist-info/zip-safe
vhr_composite-0.0.1.dist-info/RECORD
