Metadata-Version: 2.1
Name: vhr-composite
Version: 0.0.1
Summary: Very high resolution (VHR) Composite Tool
Home-page: https://github.com/nasa-nccs-hpda/vhr-composite
Author: Caleb S. Spradlin
Author-email: caleb.s.spradlin@nasa.gov
License: BSD 3-Clause License
Keywords: composite,rioxarray,rasterio
Classifier: License :: OSI Approved :: BSD License
Classifier: Programming Language :: Python :: 3
License-File: LICENSE
Requires-Dist: geopandas
Requires-Dist: rioxarray
Requires-Dist: xarray
Requires-Dist: rasterio
Requires-Dist: pandas
Requires-Dist: numba
Requires-Dist: numpy
Requires-Dist: tqdm
